gluefix.py
gluefix-0.1.1.dist-info/METADATA
gluefix-0.1.1.dist-info/WHEEL
gluefix-0.1.1.dist-info/top_level.txt
gluefix-0.1.1.dist-info/RECORD
